ddex_workbench/__init__.py
ddex_workbench/client.py
ddex_workbench/errors.py
ddex_workbench/py.typed
ddex_workbench/types.py
ddex_workbench/utils.py
ddex_workbench/validator.py
ddex_workbench-1.0.2.dist-info/licenses/LICENSE
ddex_workbench-1.0.2.dist-info/METADATA
ddex_workbench-1.0.2.dist-info/WHEEL
ddex_workbench-1.0.2.dist-info/top_level.txt
ddex_workbench-1.0.2.dist-info/RECORD
