Metadata-Version: 2.4
Name: ddex-workbench
Version: 1.0.2
Summary: Official Python SDK for DDEX Workbench - Open-source DDEX validation tools
Home-page: https://github.com/daddykev/ddex-workbench
Author: DDEX Workbench Contributors
Author-email: DDEX Workbench Contributors <support@ddex-workbench.org>
License: MIT
Project-URL: Homepage, https://ddex-workbench.org
Project-URL: Documentation, https://ddex-workbench.org/docs
Project-URL: Repository, https://github.com/daddykev/ddex-workbench
Project-URL: Issues, https://github.com/daddykev/ddex-workbench/issues
Keywords: ddex,ern,music,metadata,validation,xml,music-industry,sdk
Classifier: Development Status :: 5 - Production/Stable
Classifier: Intended Audience :: Developers
Classifier: License :: OSI Approved :: MIT License
Classifier: Programming Language :: Python :: 3
Classifier: Programming Language :: Python :: 3.7
Classifier: Programming Language :: Python :: 3.8
Classifier: Programming Language :: Python :: 3.9
Classifier: Programming Language :: Python :: 3.10
Classifier: Programming Language :: Python :: 3.11
Classifier: Programming Language :: Python :: 3.12
Classifier: Topic :: Software Development :: Libraries :: Python Modules
Classifier: Topic :: Multimedia :: Sound/Audio
Requires-Python: >=3.7
License-File: LICENSE
Requires-Dist: requests>=2.28.0
Requires-Dist: typing-extensions>=4.0.0; python_version < "3.8"
Requires-Dist: dataclasses>=0.6; python_version < "3.7"
Provides-Extra: dev
Requires-Dist: pytest>=7.0.0; extra == "dev"
Requires-Dist: pytest-cov>=4.0.0; extra == "dev"
Requires-Dist: pytest-mock>=3.10.0; extra == "dev"
Requires-Dist: black>=23.0.0; extra == "dev"
Requires-Dist: mypy>=1.0.0; extra == "dev"
Requires-Dist: flake8>=6.0.0; extra == "dev"
Requires-Dist: tox>=4.0.0; extra == "dev"
Requires-Dist: twine>=4.0.0; extra == "dev"
Dynamic: author
Dynamic: home-page
Dynamic: license-file
Dynamic: requires-python
